sun_agent_toolkit/__init__.py
sun_agent_toolkit/adapters/__init__.py
sun_agent_toolkit/adapters/autogen/__init__.py
sun_agent_toolkit/adapters/autogen/_prompts.py
sun_agent_toolkit/adapters/autogen/adapter.py
sun_agent_toolkit/adapters/autogen/agent_manager.py
sun_agent_toolkit/adapters/autogen/utils.py
sun_agent_toolkit/core/__init__.py
sun_agent_toolkit/core/classes/plugin_base.py
sun_agent_toolkit/core/classes/tool_base.py
sun_agent_toolkit/core/classes/wallet_client_base.py
sun_agent_toolkit/core/decorators/tool.py
sun_agent_toolkit/core/types/chain.py
sun_agent_toolkit/core/types/token.py
sun_agent_toolkit/core/utils/get_tools.py
sun_agent_toolkit/core/utils/snake_case.py
sun_agent_toolkit/plugins/__init__.py
sun_agent_toolkit/plugins/coingecko/__init__.py
sun_agent_toolkit/plugins/coingecko/parameters.py
sun_agent_toolkit/plugins/coingecko/plugin.py
sun_agent_toolkit/plugins/coingecko/service.py
sun_agent_toolkit/plugins/sunio/__init__.py
sun_agent_toolkit/plugins/sunio/env.py
sun_agent_toolkit/plugins/sunio/parameters.py
sun_agent_toolkit/plugins/sunio/service.py
sun_agent_toolkit/plugins/sunpump/__init__.py
sun_agent_toolkit/plugins/sunpump/abi.py
sun_agent_toolkit/plugins/sunpump/env.py
sun_agent_toolkit/plugins/sunpump/parameters.py
sun_agent_toolkit/plugins/sunpump/service.py
sun_agent_toolkit/plugins/sunpump/sunpump-openapi.json
sun_agent_toolkit/plugins/sunswap/__init__.py
sun_agent_toolkit/plugins/sunswap/parameters.py
sun_agent_toolkit/plugins/sunswap/plugin.py
sun_agent_toolkit/plugins/sunswap/service.py
sun_agent_toolkit/plugins/tronscan/__init__.py
sun_agent_toolkit/plugins/tronscan/env.py
sun_agent_toolkit/plugins/tronscan/parameters.py
sun_agent_toolkit/plugins/tronscan/plugin.py
sun_agent_toolkit/plugins/tronscan/service.py
sun_agent_toolkit/wallets/__init__.py
sun_agent_toolkit/wallets/tron/__init__.py
sun_agent_toolkit/wallets/tron/abi.py
sun_agent_toolkit/wallets/tron/params.py
sun_agent_toolkit/wallets/tron/tokens.py
sun_agent_toolkit-0.0.3b40.dist-info/METADATA
sun_agent_toolkit-0.0.3b40.dist-info/WHEEL
sun_agent_toolkit-0.0.3b40.dist-info/RECORD
