Metadata-Version: 2.4
Name: sun-agent-toolkit
Version: 0.0.3b40
Summary: Sun Agent Toolkit - TRON wallet functionality for AI agents
Author: Sun Agent Toolkit Team
License: MIT
Requires-Python: >=3.12
Requires-Dist: aiohttp>=3.8.0
Requires-Dist: autogen-agentchat>=0.4.0
Requires-Dist: autogen-core>=0.4.0
Requires-Dist: autogen-ext>=0.4.0
Requires-Dist: openai
Requires-Dist: python-dotenv>=1.0.0
Requires-Dist: tiktoken>=0.5.0
Requires-Dist: tronpy>=0.6.0
